proteas/__init__.py
proteas/combinations.py
proteas/proteas.py
proteas/unit.py
proteas/tests/__init__.py
proteas/tests/test_proteas.py
proteas/tests/test_unit.py
proteas-0.0.5.dist-info/METADATA
proteas-0.0.5.dist-info/WHEEL
proteas-0.0.5.dist-info/top_level.txt
proteas-0.0.5.dist-info/RECORD
